{
    "version": "https://jsonfeed.org/version/1",
    "title": "新浪新闻",
    "home_page_url": "https://ruanyf.github.io/sina-news/",
    "feed_url": "https://ruanyf.github.io/sina-news/rss.json",
    "description": "新浪全球实时财经新闻直播",
    "items": [
        {
            "id": 2111584,
            "content_html": "",
            "url": "https://finance.sina.cn/7x24/2021-04-08/detail-ikmyaawa8595175.d.html",
            "title": "【S&T HLDGS继续停牌】S&T HLDGS发布公告，公司主要于新加坡从事建筑服务及物业投资业务。董事谨此指出，尽管暂停买卖，本公司仍会在新加坡因公共卫生事件爆发造成的不利影响下，尽其所能继续照常开展业务。",
            "date_modified": "2021-04-08T14:08:17.000Z"
        },
        {
            "id": 2111582,
            "content_html": "",
            "url": "https://finance.sina.cn/7x24/2021-04-08/detail-ikmyaawa8594756.d.html",
            "title": "皇家加勒比邮轮将延长部分航线停航时间至6月30日。",
            "date_modified": "2021-04-08T14:04:24.000Z"
        },
        {
            "id": 2111572,
            "content_html": "",
            "url": "https://finance.sina.cn/7x24/2021-04-08/detail-ikmyaawa8594075.d.html",
            "title": "【金禾实业：2020年净利润7.19亿元 同比降11.16%】金禾实业4月8日晚间披露年报，公司2020年实现营业收入为36.66亿元，同比下滑7.69%；归母净利润7.19亿元，同比下滑11.16%；基本每股收益1.29元。每10股派发现金红利4.5元（含税）。",
            "date_modified": "2021-04-08T13:58:23.000Z"
        },
        {
            "id": 2111571,
            "content_html": "",
            "url": "https://finance.sina.cn/7x24/2021-04-08/detail-ikmxzfmk5735593.d.html",
            "title": "腾讯控股ADR涨超3%，今日腾讯港股收跌1.51%，获净买入50.65亿港元，其Naspers以595港元/股的价格出售了腾讯控股的股份。",
            "date_modified": "2021-04-08T13:57:57.000Z"
        },
        {
            "id": 2111569,
            "content_html": "",
            "url": "https://finance.sina.cn/7x24/2021-04-08/detail-ikmyaawa8593897.d.html",
            "title": "IMF：阿根廷总统的政治盟友在政策和国际货币基金组织谈判方面似乎存在重大的意见分歧。",
            "date_modified": "2021-04-08T13:56:32.000Z"
        },
        {
            "id": 2111567,
            "content_html": "",
            "url": "https://finance.sina.cn/7x24/2021-04-08/detail-ikmyaawa8593681.d.html",
            "title": "软银和富兰克林向软件供应商OneTrust投资2.1亿美元，该公司估值超过50亿美元。",
            "date_modified": "2021-04-08T13:54:27.000Z"
        },
        {
            "id": 2111566,
            "content_html": "",
            "url": "https://finance.sina.cn/7x24/2021-04-08/detail-ikmxzfmk5735233.d.html",
            "title": "美指刷新3月23日以来低位至92.123，日内跌幅扩大到0.31%。",
            "date_modified": "2021-04-08T13:54:09.000Z"
        },
        {
            "id": 2111562,
            "content_html": "",
            "url": "https://finance.sina.cn/7x24/2021-04-08/detail-ikmxzfmk5735086.d.html",
            "title": "  市场消息：据悉空客3月交付客机72架。",
            "date_modified": "2021-04-08T13:52:31.000Z"
        },
        {
            "id": 2111559,
            "content_html": "",
            "url": "https://finance.sina.cn/7x24/2021-04-08/detail-ikmxzfmk5734593.d.html",
            "title": "通用汽车跌2.4%，早前通用宣布因缺芯削减北美数家工厂的产量。",
            "date_modified": "2021-04-08T13:48:45.000Z"
        },
        {
            "id": 2111555,
            "content_html": "",
            "url": "https://finance.sina.cn/7x24/2021-04-08/detail-ikmyaawa8592766.d.html",
            "title": "【注册制审核更严、退市力度加大！资本市场改革进入“施工期”】多位市场人士表示，资本市场改革进入“施工期”，改革举措的逐步落地有利于加速打造资本市场良性生态，切实增强市场主体改革获得感，建立与发展满足不同层次不同规模的实体经济需求，充满生机活力的多层次资本市场，提升资本市场的资源配置效率。（证券时报）",
            "date_modified": "2021-04-08T13:45:56.000Z"
        },
        {
            "id": 2111554,
            "content_html": "",
            "url": "https://finance.sina.cn/7x24/2021-04-08/detail-ikmyaawa8592729.d.html",
            "title": "Nikola涨近3%，今日公司与汽车销售与维修连锁Rig360签订分销及服务协议。",
            "date_modified": "2021-04-08T13:45:33.000Z"
        },
        {
            "id": 2111552,
            "content_html": "",
            "title": "小鹏汽车涨近3%，今日武汉经济技术开发区管理委员会与小鹏汽车正式签署“小鹏汽车武汉智能网联汽车制造基地及研发中心项目投资协议”。",
            "date_modified": "2021-04-08T13:44:09.000Z"
        },
        {
            "id": 2111551,
            "content_html": "",
            "url": "https://finance.sina.cn/7x24/2021-04-08/detail-ikmyaawa8592563.d.html",
            "title": "【安图生物：拟4609万欧元出售Mobidiag部分股权】安图生物公告，公司参股公司芬兰MobidiagOy股东与美国Hologic签署股权出售协议，计划将其全部股份出售给Hologic，其中安图生物持有Mobidiag 7.63%的股权以约4609万欧元出售。",
            "date_modified": "2021-04-08T13:43:58.000Z"
        },
        {
            "id": 2111548,
            "content_html": "",
            "url": "https://finance.sina.cn/7x24/2021-04-08/detail-ikmxzfmk5734048.d.html",
            "title": "瓦莱罗能源跌2.5%，公司预计第一季度将录得亏损。",
            "date_modified": "2021-04-08T13:42:32.000Z"
        },
        {
            "id": 2111547,
            "content_html": "",
            "url": "https://finance.sina.cn/7x24/2021-04-08/detail-ikmxzfmk5733921.d.html",
            "title": "  大众集团：无法进一步开展产量调整计划。",
            "date_modified": "2021-04-08T13:41:30.000Z"
        },
        {
            "id": 2111545,
            "content_html": "",
            "url": "https://finance.sina.cn/7x24/2021-04-08/detail-ikmyaawa8592204.d.html",
            "title": "大众集团：得州寒潮加剧了芯片短缺瓶颈。",
            "date_modified": "2021-04-08T13:41:02.000Z"
        },
        {
            "id": 2111544,
            "content_html": "",
            "url": "https://finance.sina.cn/7x24/2021-04-08/detail-ikmyaawa8592132.d.html",
            "title": "  大众集团：预计芯片供应在未来数月仍将紧俏。",
            "date_modified": "2021-04-08T13:40:33.000Z"
        },
        {
            "id": 2111543,
            "content_html": "",
            "title": "德意志银行：将再次召开2021年年会；整个股东大会，包括一般性辩论和投票，将首次通过互联网公开直播；打算从2022年开始，在成功的战略执行和监管批准的情况下，恢复2021财年的资本回报。",
            "date_modified": "2021-04-08T13:40:09.000Z"
        },
        {
            "id": 2111542,
            "content_html": "",
            "url": "https://finance.sina.cn/7x24/2021-04-08/detail-ikmyaawa8591927.d.html",
            "title": "腾讯控股：谨订于二零二一年五月二十日下午举行股东周年大会。",
            "date_modified": "2021-04-08T13:39:07.000Z"
        },
        {
            "id": 2111541,
            "content_html": "",
            "url": "https://finance.sina.cn/7x24/2021-04-08/detail-ikmxzfmk5733509.d.html",
            "title": "芝商所将与Fastmarket公司合作于5月3日推出锂期货。",
            "date_modified": "2021-04-08T13:38:50.000Z"
        },
        {
            "id": 2111540,
            "content_html": "",
            "url": "https://finance.sina.cn/7x24/2021-04-08/detail-ikmyaawa8591842.d.html",
            "title": "通用汽车表示将继续利用所有可用的半导体来制造和运输最受欢迎和需求的产品，包括全尺寸卡车和suv。",
            "date_modified": "2021-04-08T13:38:23.000Z"
        },
        {
            "id": 2111538,
            "content_html": "",
            "url": "https://finance.sina.cn/7x24/2021-04-08/detail-ikmxzfmk5733336.d.html",
            "title": "【北京房贷利率“暂未上调”、部分银行无额度放款】北京商报记者对北京地区多家国有大行、股份制银行网点进行调查，多位银行个贷中心客户经理向北京商报记者表示，暂未接到上调房贷利率的通知，目前北京地区房贷利率均按照监管规定执行首套房利率为LPR（贷款市场报价利率）+55个基点（5.2%），二套房利率LPR+105个基点（5.7%）。不过有部分股份制银行出现了放贷收紧情况，更有相关银行人士透露“目前行内已无放款额度”。",
            "date_modified": "2021-04-08T13:37:13.000Z"
        },
        {
            "id": 2111537,
            "content_html": "",
            "url": "https://finance.sina.cn/7x24/2021-04-08/detail-ikmyaawa8591682.d.html",
            "title": "Riot Blockchain涨超6%，公司宣布收购矿企Whinstone，打造美国领先的区块链企业。",
            "date_modified": "2021-04-08T13:36:54.000Z"
        },
        {
            "id": 2111536,
            "content_html": "",
            "url": "https://finance.sina.cn/7x24/2021-04-08/detail-ikmxzfmk5733213.d.html",
            "title": "荔枝涨5%，公司宣布与蚂蚁链达成合作协议，以促进采用区块链技术的播客版权保护。",
            "date_modified": "2021-04-08T13:36:01.000Z"
        },
        {
            "id": 2111531,
            "content_html": "",
            "url": "https://finance.sina.cn/7x24/2021-04-08/detail-ikmxzfmk5732938.d.html",
            "title": "英镑兑日元刚刚触及150.00关口，最新报150.00，日跌0.60%。",
            "date_modified": "2021-04-08T13:32:53.000Z"
        },
        {
            "id": 2111530,
            "content_html": "",
            "url": "https://finance.sina.cn/7x24/2021-04-08/detail-ikmxzfmk5732914.d.html",
            "title": "  游戏驿站高开超4%，公司投资人Ryan Cohen将在年度股东大会后获选为董事会主席。",
            "date_modified": "2021-04-08T13:32:36.000Z"
        },
        {
            "id": 2111529,
            "content_html": "",
            "url": "https://finance.sina.cn/7x24/2021-04-08/detail-ikmyaawa8591286.d.html",
            "title": "  中概股联代科技美股跌近15%，昨日收涨超110%。",
            "date_modified": "2021-04-08T13:32:28.000Z"
        },
        {
            "id": 2111523,
            "content_html": "",
            "url": "https://finance.sina.cn/7x24/2021-04-08/detail-ikmyaawa8591017.d.html",
            "title": "  多伦多股票指数开盘上涨27.95点，涨幅0.15%，至19157.02点。",
            "date_modified": "2021-04-08T13:30:30.000Z"
        },
        {
            "id": 2111521,
            "content_html": "",
            "url": "https://finance.sina.cn/7x24/2021-04-08/detail-ikmyaawa8590691.d.html",
            "title": "据媒体消息，通用汽车预计本次减产将对本年营业收入造成15亿-20亿美元的损失，减产的影响将会计入公司本年的财务报表中。",
            "date_modified": "2021-04-08T13:28:07.000Z"
        },
        {
            "id": 2111520,
            "content_html": "",
            "url": "https://finance.sina.cn/7x24/2021-04-08/detail-ikmxzfmk5732330.d.html",
            "title": "【协鑫能科年度报告：2020年净利同比增44.8% 拟10派1.5元】协鑫能科披露年报，公司2020年实现营业收入为113.06亿元，同比上年调整后增长3.74%；归母净利润8.02亿元，同比增长44.80%；基本每股收益0.59元。每10股派发现金红利1.5元（含税）。",
            "date_modified": "2021-04-08T13:27:36.000Z"
        },
        {
            "id": 2111517,
            "content_html": "",
            "url": "https://finance.sina.cn/7x24/2021-04-08/detail-ikmxzfmk5731898.d.html",
            "title": "通用汽车盘前走低，此前有媒体报道称通用削减了北美数家工厂的产量。",
            "date_modified": "2021-04-08T13:24:03.000Z"
        },
        {
            "id": 2111516,
            "content_html": "",
            "url": "https://finance.sina.cn/7x24/2021-04-08/detail-ikmyaawa8590178.d.html",
            "title": "【紫光国微：与中汽中心达成战略合作】4月8日，汽车芯片战略合作联合发布会暨第一届汽车芯片安全技术研讨会在天津举办，紫光国微在会上与中国汽车技术研究中心签订汽车芯片战略合作协议，双方将共同开展汽车芯片领域前沿技术的创新与应用，为汽车的智能网联化发展构筑坚实的安全堡垒。",
            "date_modified": "2021-04-08T13:23:36.000Z"
        },
        {
            "id": 2111513,
            "content_html": "",
            "url": "https://finance.sina.cn/7x24/2021-04-08/detail-ikmxzfmk5731509.d.html",
            "title": "媒体消息：因芯片短缺，通用汽车削减了北美数个工厂的产量。",
            "date_modified": "2021-04-08T13:21:19.000Z"
        },
        {
            "id": 2111511,
            "content_html": "",
            "url": "https://finance.sina.cn/7x24/2021-04-08/detail-ikmxzfmk5731407.d.html",
            "title": "五菱宏光MINI EV马卡龙版正式上市，新车同样推出120（时尚款）、170km（臻享款）续航两款车型，售价分别为37600元、43600元。",
            "date_modified": "2021-04-08T13:20:45.000Z"
        },
        {
            "id": 2111509,
            "content_html": "",
            "url": "https://finance.sina.cn/7x24/2021-04-08/detail-ikmyaawa8589575.d.html",
            "title": "  市场消息：普拉格能源受邀竞标美国能源部价值5.2亿美元的担保贷款计划。",
            "date_modified": "2021-04-08T13:19:29.000Z"
        },
        {
            "id": 2111507,
            "content_html": "",
            "url": "https://finance.sina.cn/7x24/2021-04-08/detail-ikmxzfmk5731130.d.html",
            "title": "【北斗专家回应“掉线”：具体原因不好评价】近日，因大货车北斗卫星定位装置掉线被罚款2000元，货车司机金德强发生不幸一事引发关注。4月8日，北斗卫星导航系统专家表示，在卫星导航系统的设计中，已经通过星座和卫星可靠性等设计保证定位授时服务的连续不间断。通常，用户可以见到的北斗卫星数量大大多于4颗，我国及周边更是达到十几颗，可以保证定位授时服务连续稳定。对于此次大货车卫星定位掉线事件，具体原因不好评价，从北斗系统提供服务的角度，北斗能保证可见卫星数和信号质量，从而保证定位。这个位置信息到中心还有诸多环节，里面有很多技术和管理上的细节，这些细节可能得具体分析。（贝壳财经）",
            "date_modified": "2021-04-08T13:18:55.000Z"
        },
        {
            "id": 2111504,
            "content_html": "",
            "url": "https://finance.sina.cn/7x24/2021-04-08/detail-ikmyaawa8589329.d.html",
            "title": "【深圳瑞捷中签号出炉，共2.24万个】深圳瑞捷4月8日晚间披露网上中签结果，中签号码共22400个，每个中签号码只能认购500股深圳瑞捷工程咨询股份有限公司A股股票。",
            "date_modified": "2021-04-08T13:16:49.000Z"
        },
        {
            "id": 2111502,
            "content_html": "",
            "url": "https://finance.sina.cn/7x24/2021-04-08/detail-ikmyaawa8589185.d.html",
            "title": "【伯特利年度报告：2020年净利润同比增长15% 拟10派1.18元】伯特利发布年报，实现营业收入30.41亿元，同比减少3.63%；净利润4.61亿元，同比增长14.93%；基本每股收益1.13元；拟10派1.18元。",
            "date_modified": "2021-04-08T13:15:38.000Z"
        },
        {
            "id": 2111501,
            "content_html": "",
            "url": "https://finance.sina.cn/7x24/2021-04-08/detail-ikmyaawa8589177.d.html",
            "title": "【海航与空客签署合作框架协议】4月8日，海航集团旗下海航航空集团、海南航空与空客在海口海航大厦举行会谈并签署合作框架协议。双方将发挥各自资源优势，在经营性债务、机队引进、飞机维修、飞行训练等方面进一步加强深度合作，确保运行安全平稳，共同助推中国民航高质量发展。",
            "date_modified": "2021-04-08T13:15:28.000Z"
        },
        {
            "id": 2111500,
            "content_html": "",
            "url": "https://finance.sina.cn/7x24/2021-04-08/detail-ikmxzfmk5730645.d.html",
            "title": "【货运公司满帮集团即将赴美上市】满帮集团即将赴美 IPO，募资额将超过10亿美元，市值区间为220 亿-300亿美元，上市辅导机构为摩根士丹利与中金公司。知情人士称，“满帮很快就会公开交表，预计4月底5月初就会上市。” (财经)",
            "date_modified": "2021-04-08T13:14:16.000Z"
        },
        {
            "id": 2111499,
            "content_html": "",
            "url": "https://finance.sina.cn/7x24/2021-04-08/detail-ikmyaawa8588942.d.html",
            "title": "【*ST华映：2020年净利润6.11亿元 申请撤销退市风险警示】*ST华映发布年报，2020年归母净利润6.11亿元，上年同期净亏损25.87亿元，扭亏为盈；营业收入21.94亿元，同比增长48.83%；基本每股收益0.221元。公司已向深圳证券交易所提交了对公司股票交易撤销退市风险警示的申请。",
            "date_modified": "2021-04-08T13:13:25.000Z"
        },
        {
            "id": 2111497,
            "content_html": "",
            "url": "https://finance.sina.cn/7x24/2021-04-08/detail-ikmyaawa8588722.d.html",
            "title": "摩根士丹利：将IBM目标价从140美元上调至150美元。",
            "date_modified": "2021-04-08T13:11:18.000Z"
        },
        {
            "id": 2111495,
            "content_html": "",
            "url": "https://finance.sina.cn/7x24/2021-04-08/detail-ikmxzfmk5730024.d.html",
            "title": "和而泰：拟分拆所属子公司浙江铖昌科技股份有限公司至A股上市。",
            "date_modified": "2021-04-08T13:09:42.000Z"
        },
        {
            "id": 2111494,
            "content_html": "",
            "url": "https://finance.sina.cn/7x24/2021-04-08/detail-ikmyaawa8588365.d.html",
            "title": "【美格智能：预计一季度净利润同比增长255%-302%】美格智能公告，一季度预计净利润约1500万元~1700万元，同比增长255.02%~302.36%。业绩变动原因：公司精密组件业务完全剥离后，无线通信模组及解决方案业务订单充足，其中应用于智能网联车，固定无线接入(FWA)领域及5G产品出货量较去年同期大幅上升，整体营业收入较去年同期大幅增长。",
            "date_modified": "2021-04-08T13:08:58.000Z"
        },
        {
            "id": 2111492,
            "content_html": "",
            "url": "https://finance.sina.cn/7x24/2021-04-08/detail-ikmyaawa8588107.d.html",
            "title": "【北京：外卖禁用不可降解塑料袋】北京市市场监督管理局日前发布北京市塑料污染治理工作详解，规定北京建成区范围内外卖禁止使用不可降解塑料袋，建成区、景区景点堂食禁止使用不可降解一次性塑料餐具。（新华社）",
            "date_modified": "2021-04-08T13:07:07.000Z"
        },
        {
            "id": 2111490,
            "content_html": "",
            "url": "https://finance.sina.cn/7x24/2021-04-08/detail-ikmxzfmk5729580.d.html",
            "title": "【新一代华为智慧屏V系列售价5499元起】新一代华为智慧屏V系列售价5499元起，华为全屋智能尊享版售价99999元起。",
            "date_modified": "2021-04-08T13:06:22.000Z"
        },
        {
            "id": 2111487,
            "content_html": "",
            "url": "https://finance.sina.cn/7x24/2021-04-08/detail-ikmyaawa8587867.d.html",
            "title": "横河模具：公司名称拟变更为宁波横河精密工业股份有限公司，证券简称变更为横河精密。",
            "date_modified": "2021-04-08T13:05:46.000Z"
        },
        {
            "id": 2111486,
            "content_html": "",
            "url": "https://finance.sina.cn/7x24/2021-04-08/detail-ikmxzfmk5729457.d.html",
            "title": "【*ST盐湖：向深圳证券交易所提出恢复上市申请】*ST盐湖：董事会认为公司已符合提出恢复上市申请的条件，并于 2021 年 3 月 30 日，召开第八届董事会第三次会议，审议通过了《公司符合恢复上市条件及申请恢复上市的报告》的议案。2021年 4 月 8 日，公司向深圳证券交易所提交了股票恢复上市的书面申请。",
            "date_modified": "2021-04-08T13:05:35.000Z"
        },
        {
            "id": 2111485,
            "content_html": "",
            "url": "https://finance.sina.cn/7x24/2021-04-08/detail-ikmyaawa8587730.d.html",
            "title": "6天5板金发拉比收关注函：要求详细分析韩妃投资评估高额增值的原因，以及本次交易作价的合理性、公允性。",
            "date_modified": "2021-04-08T13:04:52.000Z"
        },
        {
            "id": 2111483,
            "content_html": "",
            "url": "https://finance.sina.cn/7x24/2021-04-08/detail-ikmxzfmk5729171.d.html",
            "title": "【瑞信：股价回调后 将B站评级上调至跑赢大市】瑞信分析师Kenneth Fong将哔哩哔哩的评级从中性上调至 \"跑赢大盘\"，目标价从150美元下调至140美元。尽管近期B站股价出现回调，但该分析师认为基本面变化不大，公司对于用户增长、流量变现潜力和独特产品的股市一如既往。Fong仍看好哔哩哔哩，认为尽管B站面临激烈竞争，用户数量增速仍较快；丰富的内容有助于提高用户参与度。此外，该分析师认为广告业务增长超出市场预期，以及港交所二次上市，也是B站股价的催化剂。",
            "date_modified": "2021-04-08T13:03:27.000Z"
        },
        {
            "id": 2111481,
            "content_html": "",
            "url": "https://finance.sina.cn/7x24/2021-04-08/detail-ikmxzfmk5729111.d.html",
            "title": "  市场消息：在达成合作协议后，Beyond Meat将在美国全国超过5000家连锁杂货店中销售期产品。",
            "date_modified": "2021-04-08T13:03:07.000Z"
        }
    ]
}